{
  "content": [
    {
      "content": null,
      "created": "2025-05-17T16:44:41.638641Z",
      "format": null,
      "hash": null,
      "hash_algorithm": null,
      "last_modified": "2025-05-17T16:44:38.910629Z",
      "mimetype": "text/markdown",
      "name": "README.md",
      "path": "README.md",
      "size": 84,
      "type": "file",
      "writable": true
    }
  ],
  "created": "2025-05-17T16:44:41.638641Z",
  "format": "json",
  "hash": null,
  "hash_algorithm": null,
  "last_modified": "2025-05-17T16:44:41.638641Z",
  "mimetype": null,
  "name": "",
  "path": "",
  "size": null,
  "type": "directory",
  "writable": true
}